setup.py
dsm_cb/__init__.py
dsm_cb/db_connection.py
dsm_cb/start.py
dsm_cb.egg-info/PKG-INFO
dsm_cb.egg-info/SOURCES.txt
dsm_cb.egg-info/dependency_links.txt
dsm_cb.egg-info/requires.txt
dsm_cb.egg-info/top_level.txt