Metadata-Version: 1.0
Name: dsm-cb
Version: 0.1
Summary: A package to log daily tasks
Home-page: UNKNOWN
Author: Chintan Bhatt
Author-email: UNKNOWN
License: UNKNOWN
Platform: UNKNOWN
